PinInPy/__init__.py
PinInPy/_pinin4cpp_cffi.pyd
PinInPy/PinIn4Cpp/LICENSE
PinInPy/PinIn4Cpp/licenses/PinIn.txt
PinInPy/PinIn4Cpp/licenses/pinyin-data.txt
pininpy-1.0.2.dist-info/METADATA
pininpy-1.0.2.dist-info/WHEEL
pininpy-1.0.2.dist-info/licenses/LICENSE
pininpy-1.0.2.dist-info/RECORD
