Metadata-Version: 2.2
Name: PinInPy
Version: 1.0.2
Summary: Python library for Pinyin searching
Keywords: PinIn,pinyin match,pinyin,cffi
Author-Email: SajoYukimi <kagiyamahino@gmail.com>
License: MIT
Classifier: Development Status :: 5 - Production/Stable
Classifier: Intended Audience :: Developers
Classifier: License :: OSI Approved :: MIT License
Classifier: Operating System :: MacOS :: MacOS X
Classifier: Operating System :: Microsoft :: Windows
Classifier: Operating System :: POSIX :: Linux
Classifier: Programming Language :: Python :: 3
Classifier: Programming Language :: Python :: 3.9
Classifier: Programming Language :: Python :: 3.10
Classifier: Programming Language :: Python :: 3.11
Classifier: Programming Language :: Python :: 3.12
Classifier: Programming Language :: Python :: 3.13
Classifier: Programming Language :: Python :: 3.14
Classifier: Programming Language :: C++
Classifier: Topic :: Software Development :: Libraries :: Python Modules
Classifier: Natural Language :: Chinese (Simplified)
Classifier: Natural Language :: Chinese (Traditional)
Project-URL: Homepage, https://github.com/KagiamamaHIna/PinInPy
Project-URL: Bug Tracker, https://github.com/KagiamamaHIna/PinInPy/issues
Project-URL: Source, https://github.com/KagiamamaHIna/PinInPy
Requires-Python: >=3.9
Requires-Dist: cffi
